{
  "cache": {
    "manifest_path": "data/curriculum_runs/calls48_loop_iter19/splits/split_manifest.json",
    "reason": "manifest_missing",
    "reused": false
  },
  "coverage": {
    "fields": [
      "compiler_version",
      "optimizer",
      "visibility",
      "source",
      "length_bucket",
      "function_family"
    ],
    "holdout": {
      "fields": {
        "compiler_version": {
          "0.5.16": 5,
          "0.5.17": 2,
          "0.6.12": 2
        },
        "function_family": {
          "other": 7,
          "read_getter": 2
        },
        "length_bucket": {
          "257-512": 3,
          "<=256": 6
        },
        "optimizer": {
          "disabled": 2,
          "enabled": 7
        },
        "source": {
          "huggingface": 9
        },
        "visibility": {
          "external": 7,
          "public": 2
        }
      },
      "row_count": 9
    },
    "min_holdout_stratum_count": 0,
    "splits": {
      "test": {
        "fields": {
          "compiler_version": {
            "0.5.17": 2,
            "0.6.12": 2
          },
          "function_family": {
            "other": 2,
            "read_getter": 2
          },
          "length_bucket": {
            "257-512": 3,
            "<=256": 1
          },
          "optimizer": {
            "disabled": 1,
            "enabled": 3
          },
          "source": {
            "huggingface": 4
          },
          "visibility": {
            "external": 2,
            "public": 2
          }
        },
        "group_count": 2,
        "row_count": 4
      },
      "train": {
        "fields": {
          "compiler_version": {
            "0.5.11": 1,
            "0.5.12": 1,
            "0.5.17": 8,
            "0.5.8": 1,
            "0.6.0": 1,
            "0.6.12": 17,
            "0.6.6": 1,
            "0.7.4": 1,
            "0.8.20": 3,
            "0.8.26": 5
          },
          "function_family": {
            "burn": 1,
            "mint": 1,
            "other": 33,
            "read_getter": 3,
            "write_setter": 1
          },
          "length_bucket": {
            "257-512": 15,
            "513-1024": 7,
            "<=256": 17
          },
          "optimizer": {
            "disabled": 13,
            "enabled": 26
          },
          "source": {
            "huggingface": 39
          },
          "visibility": {
            "external": 22,
            "public": 17
          }
        },
        "group_count": 38,
        "row_count": 39
      },
      "val": {
        "fields": {
          "compiler_version": {
            "0.5.16": 5
          },
          "function_family": {
            "other": 5
          },
          "length_bucket": {
            "<=256": 5
          },
          "optimizer": {
            "disabled": 1,
            "enabled": 4
          },
          "source": {
            "huggingface": 5
          },
          "visibility": {
            "external": 5
          }
        },
        "group_count": 1,
        "row_count": 5
      }
    },
    "status": "passed",
    "total": {
      "fields": {
        "compiler_version": {
          "0.5.11": 1,
          "0.5.12": 1,
          "0.5.16": 5,
          "0.5.17": 10,
          "0.5.8": 1,
          "0.6.0": 1,
          "0.6.12": 19,
          "0.6.6": 1,
          "0.7.4": 1,
          "0.8.20": 3,
          "0.8.26": 5
        },
        "function_family": {
          "burn": 1,
          "mint": 1,
          "other": 40,
          "read_getter": 5,
          "write_setter": 1
        },
        "length_bucket": {
          "257-512": 18,
          "513-1024": 7,
          "<=256": 23
        },
        "optimizer": {
          "disabled": 15,
          "enabled": 33
        },
        "source": {
          "huggingface": 48
        },
        "visibility": {
          "external": 29,
          "public": 19
        }
      },
      "row_count": 48
    },
    "violation_count": 0,
    "violations": []
  },
  "created_at": "2026-06-28T03:33:03Z",
  "group_counts": {
    "source": 41,
    "test": 2,
    "train": 38,
    "val": 1
  },
  "input_sha256": "94237195b2a55ae3d0065658180c53a63236a0b4c616677bc47efa2b8f00997d",
  "leakage_validation": {
    "checked_categories": [
      "source_hash",
      "contract_address",
      "contract_function",
      "body_hash",
      "input_hash",
      "output_hash"
    ],
    "overlap_counts": {
      "body_hash": 0,
      "contract_address": 0,
      "contract_function": 0,
      "input_hash": 0,
      "output_hash": 0,
      "source_hash": 0
    },
    "sample_overlaps": [],
    "status": "passed",
    "total_overlap_keys": 0
  },
  "manifest_kind": "dataset_split",
  "outputs": {
    "test": {
      "artifact_type": "file",
      "dataset_artifact_type": "derived_split_artifact",
      "dataset_role": "test_split",
      "exists": true,
      "modified_at": "2026-06-28T03:33:03Z",
      "path": "data/curriculum_runs/calls48_loop_iter19/splits/test_dataset.jsonl",
      "row_count": 4,
      "sha256": "cd10b23ecb2f5089ac6a4a20cd6ce6a475eaf126c24eba9567e0c1da6de77874",
      "size_bytes": 16618
    },
    "train": {
      "artifact_type": "file",
      "dataset_artifact_type": "derived_split_artifact",
      "dataset_role": "train_split",
      "exists": true,
      "modified_at": "2026-06-28T03:33:03Z",
      "path": "data/curriculum_runs/calls48_loop_iter19/splits/train_dataset.jsonl",
      "row_count": 39,
      "sha256": "1d469e9eda231cfa20592e30e2e4f4b263f6b41af6268c96e9d485a29c58af39",
      "size_bytes": 158072
    },
    "val": {
      "artifact_type": "file",
      "dataset_artifact_type": "derived_split_artifact",
      "dataset_role": "validation_split",
      "exists": true,
      "modified_at": "2026-06-28T03:33:03Z",
      "path": "data/curriculum_runs/calls48_loop_iter19/splits/val_dataset.jsonl",
      "row_count": 5,
      "sha256": "f68e68a1f8f78a867a60c34c2d1fa469a2f68702d7ae43cf421369451a9562b7",
      "size_bytes": 13491
    }
  },
  "parameters": {
    "allow_degenerate_splits": true,
    "group_key_precedence": [
      "source_hash",
      "contract_address",
      "contract_function",
      "body_hash",
      "output_hash",
      "input_hash"
    ],
    "leakage_key_categories": [
      "source_hash",
      "contract_address",
      "contract_function",
      "body_hash",
      "input_hash",
      "output_hash"
    ],
    "max_component_target_ratio": 1.0,
    "min_holdout_stratum_count": 0,
    "min_split_target_ratio": 0.5,
    "seed": 42,
    "stratification_fields": [
      "compiler_version",
      "optimizer",
      "visibility",
      "source",
      "length_bucket",
      "function_family"
    ],
    "test_ratio": 0.05000000000000002,
    "train_ratio": 0.85,
    "val_ratio": 0.1
  },
  "row_counts": {
    "source": 48,
    "test": 4,
    "train": 39,
    "val": 5
  },
  "schema_version": 2,
  "source_dataset": {
    "artifact_type": "file",
    "dataset_artifact_type": "full_source_dataset",
    "dataset_role": "source",
    "exists": true,
    "modified_at": "2026-06-28T03:25:01Z",
    "path": "data/curriculum/calls48_nonoverlap.jsonl",
    "row_count": 48,
    "sha256": "94237195b2a55ae3d0065658180c53a63236a0b4c616677bc47efa2b8f00997d",
    "size_bytes": 188181
  },
  "split_quality": {
    "allow_degenerate_splits": true,
    "component_count": 41,
    "largest_component_ratio": 0.10416666666666667,
    "largest_component_rows": 5,
    "largest_components": [
      5,
      2,
      2,
      2,
      1,
      1,
      1,
      1,
      1,
      1
    ],
    "max_component_target_ratio": 1.0,
    "min_split_target_ratio": 0.5,
    "row_counts": {
      "test": 4,
      "train": 39,
      "val": 5
    },
    "status": "passed",
    "target_rows": {
      "test": 2.400000000000001,
      "train": 40.8,
      "val": 4.800000000000001
    },
    "target_vs_actual": {
      "test": {
        "actual": 4,
        "actual_to_target_ratio": 1.666666666666666,
        "delta": 1.5999999999999992,
        "target": 2.400000000000001
      },
      "train": {
        "actual": 39,
        "actual_to_target_ratio": 0.9558823529411765,
        "delta": -1.7999999999999972,
        "target": 40.8
      },
      "val": {
        "actual": 5,
        "actual_to_target_ratio": 1.0416666666666665,
        "delta": 0.1999999999999993,
        "target": 4.800000000000001
      }
    },
    "total_rows": 48,
    "violation_count": 0,
    "violations": []
  }
}